{
  "AAPL": "Apple Inc.",
  "MSFT": "Microsoft Corporation",
  "CROX": "Crocs, Inc.",
  "HRMY": "Harmony Biosciences Holdings, Inc.",
  "METC": "Ramaco Resources, Inc.",
  "SHEN": "Shenandoah Telecommunications Company",
  "NVRI": "Enviri Corporation",
  "A": "Agilent Technologies, Inc.",
  "AA": "Alcoa Corporation",
  "AAL": "American Airlines Group Inc.",
  "AAMI": "Acadian Asset Management Inc.",
  "AAOI": "Applied Optoelectronics, Inc.",
  "AAON": "AAON, Inc.",
  "AAP": "Advance Auto Parts, Inc.",
  "AAT": "American Assets Trust, Inc.",
  "ABBV": "AbbVie Inc.",
  "ABCB": "Ameris Bancorp",
  "ABG": "Asbury Automotive Group, Inc.",
  "ABM": "ABM Industries Incorporated",
  "ABNB": "Airbnb, Inc.",
  "ABR": "Arbor Realty Trust, Inc.",
  "ABT": "Abbott Laboratories",
  "ACA": "Arcosa, Inc.",
  "ACAD": "ACADIA Pharmaceuticals Inc.",
  "ACGL": "Arch Capital Group Ltd.",
  "ACHC": "Acadia Healthcare Company, Inc.",
  "ACHR": "Archer Aviation Inc.",
  "ACI": "Albertsons Companies, Inc.",
  "ACIW": "ACI Worldwide, Inc.",
  "ACLS": "Axcelis Technologies, Inc.",
  "ACM": "AECOM",
  "ACMR": "ACM Research, Inc.",
  "ACN": "Accenture plc",
  "ACNT": "Ascent Industries Co.",
  "ACRS": "Aclaris Therapeutics, Inc.",
  "ACT": "Enact Holdings, Inc.",
  "ADAM": "Adamas Trust, Inc.",
  "ADBE": "Adobe Inc.",
  "ADC": "Agree Realty Corporation",
  "ADEA": "Adeia Inc.",
  "ADI": "Analog Devices, Inc.",
  "ADM": "Archer-Daniels-Midland Company",
  "ADMA": "ADMA Biologics, Inc.",
  "ADNT": "Adient plc",
  "ADP": "Automatic Data Processing, Inc.",
  "ADSK": "Autodesk, Inc.",
  "ADT": "ADT Inc.",
  "ADUS": "Addus HomeCare Corporation",
  "AEE": "Ameren Corporation",
  "AEIS": "Advanced Energy Industries, Inc.",
  "AEO": "American Eagle Outfitters, Inc.",
  "AEP": "American Electric Power Company, Inc.",
  "AES": "The AES Corporation",
  "AESI": "Atlas Energy Solutions Inc.",
  "AFG": "American Financial Group, Inc.",
  "AFL": "Aflac Incorporated"
}